pytest_avoidance.py
pytest_avoidance-0.3.0.dist-info/LICENSE
pytest_avoidance-0.3.0.dist-info/METADATA
pytest_avoidance-0.3.0.dist-info/WHEEL
pytest_avoidance-0.3.0.dist-info/entry_points.txt
pytest_avoidance-0.3.0.dist-info/top_level.txt
pytest_avoidance-0.3.0.dist-info/RECORD
